alu4.v

module alu4(input[3:0] A, input[3:0] B, input[3:0] opcode ,output [3:0] Y,
   output [3:0] flags ) ;
   reg [3:0]Y;
   reg [3:0]flags;
   reg [3:0] tempA;
   reg [3:0] tempB;
   always @(A or B or opcode)
     begin
        tempA = ~A;
        tempB = ~B;
        flags[3]=0;
      case(opcode) //cf
        0 : Y = A ;
        1 : {flags[3], Y} = A + 1;
        2 : {flags[3],Y} = tempA + B;
        3 : {flags[3], Y} = A + B +1 ;
        4 : {flags[3], Y} = A & tempB;
        5 : {flags[3], Y} = A | B;
        6 : Y = A ^ B;
        7 : {flags[3], Y} = A << 1;
        8 : Y = ~A ;
        9 : Y = A >> 1;
        10 : {flags[3],Y} = A - B;
        11 : {flags[3], Y} = A - B - 1;
        12 : Y = ~(A & B);
        13 : Y = ~(A | B);
        14 : Y = ~(A ^ B);
        default: Y=4'bxxxx;
		endcase
	end
		always @(Y)
			begin
					flags[2] = (Y == 0000) ? 1 : 0; //zf
          			flags[1] = (^Y == 1) ? 0 : 1; //pf
           			//flags[0] = (((opcode==11)&&({flags[3],Y==5'b11111}))||(((opcode==10)||(opcode==9))&&(flags[3]==1))) ? 1 : 0 ; //sf
 					if(((opcode==9)||(opcode==10))&&(flags[3]==1))
    				  flags[0]=1;
				    else if((opcode==11)&&({flags[3],Y}==5'b11111))
				      flags[0]=1;
				    else
				      flags[0]=0;
 			end
endmodule

alutb.v

module alu_tb;

   reg[3:0] A;
   reg[3:0] B;
   wire [3:0] Y;
   reg [3:0] opcode;
   wire [3:0] flags;


integer  i;
   integer j;
   integer k;


alu4 my_alu( A, B , opcode, Y, flags);

initial
begin
   #1 $monitor("A = %b", A, " B = %b", B, "  |  opcode = %b", opcode, "  |  Y =%b", Y ," | flags = %b", flags );
   $dumpfile("test.vcd");
   $dumpvars(0,alu_tb);
   A = 0110;
   B = 1110;

           for( j =0 ; j<= 14; j = j + 1)
             begin
                opcode = j ;#5;
             end
   A = 1111;
   B = 1001;
   for( j = 0 ; j<= 14 ; j=j+1)
     begin
        opcode = j;
 #5;
        end

      $display("--------------------------------------------");



end
endmodule

test.vcd
$date
	Tue Jan 27 11:37:48 2015
$end
$version
	Icarus Verilog
$end
$timescale
	1s
$end
$scope module alu_tb $end
$var wire 4 ! Y [3:0] $end
$var wire 4 " flags [3:0] $end
$var reg 4 # A [3:0] $end
$var reg 4 $ B [3:0] $end
$var integer 32 % j [31:0] $end
$var reg 4 & opcode [3:0] $end
$scope module my_alu $end
$var wire 4 ' A [3:0] $end
$var wire 4 ( B [3:0] $end
$var wire 4 ) opcode [3:0] $end
$var reg 4 * Y [3:0] $end
$var reg 4 + flags [3:0] $end
$var reg 4 , tempA [3:0] $end
$var reg 4 - tempB [3:0] $end
$upscope $end
$upscope $end
$enddefinitions $end
#1
$dumpvars
b1001 -
b1 ,
b0 +
b1110 *
b0 )
b110 (
b1110 '
b0 &
b0 %
b110 $
b1110 #
b0 "
b1110 !
$end
#6
b10 "
b1111 *
b1111 !
b10 +
b1 &
b1 )
b1 %
#11
b0 "
b111 *
b111 !
b0 +
b10 &
b10 )
b10 %
#16
b1010 "
b101 *
b101 !
b1010 +
b11 &
b11 )
b11 %
#21
b1000 *
b1000 !
b0 +
b0 "
b100 &
b100 )
b100 %
#26
b1110 *
b1110 !
b0 +
b101 &
b101 )
b101 %
#31
b1000 *
b1000 !
b0 +
b110 &
b110 )
b110 %
#36
b1010 "
b1100 *
b1100 !
b1010 +
b111 &
b111 )
b111 %
#41
b1 *
b1 !
b0 +
b0 "
b1000 &
b1000 )
b1000 %
#46
b111 *
b111 !
b0 +
b1001 &
b1001 )
b1001 %
#51
b1000 *
b1000 !
b0 +
b1010 &
b1010 )
b1010 %
#56
b111 *
b111 !
b0 +
b1011 &
b1011 )
b1011 %
#61
b10 "
b1001 *
b1001 !
b10 +
b1100 &
b1100 )
b1100 %
#66
b0 "
b1 *
b1 !
b0 +
b1101 &
b1101 )
b1101 %
#71
b111 *
b111 !
b0 +
b1110 &
b1110 )
b1110 %
#76
b0 +
b110 -
b1000 ,
b0 &
b0 )
b1001 $
b1001 (
b111 #
b111 '
b0 %
#81
b1000 *
b1000 !
b0 +
b1 &
b1 )
b1 %
#86
b1000 "
b1 *
b1 !
b1000 +
b10 &
b10 )
b10 %
#91
b1000 +
b1000 "
b11 &
b11 )
b11 %
#96
b110 *
b110 !
b10 +
b10 "
b100 &
b100 )
b100 %
#101
b1111 *
b1111 !
b10 +
b101 &
b101 )
b101 %
#106
b0 "
b1110 *
b1110 !
b0 +
b110 &
b110 )
b110 %
#111
b0 +
b111 &
b111 )
b111 %
#116
b1000 *
b1000 !
b0 +
b1000 &
b1000 )
b1000 %
#121
b10 "
b11 *
b11 !
b10 +
b1001 &
b1001 )
b1001 %
#126
b1001 "
b1110 *
b1110 !
b1001 +
b1010 &
b1010 )
b1010 %
#131
b1101 *
b1101 !
b1000 +
b1000 "
b1011 &
b1011 )
b1011 %
#136
b1110 *
b1110 !
b0 +
b0 "
b1100 &
b1100 )
b1100 %
#141
b110 "
b0 *
b0 !
b110 +
b1101 &
b1101 )
b1101 %
#146
b0 "
b1 *
b1 !
b0 +
b1110 &
b1110 )
b1110 %
#151
b1111 %
